<service>
	<parameter name="ServiceClass" locked="false">net.webtech.GardenService</parameter>
	<operation name="queryA">
		<messageReceiver class="org.apache.axis2.rpc.receivers.RPCMessageReceiver"/>
	</operation>
	<operation name="queryB">
		<messageReceiver class="org.apache.axis2.rpc.receivers.RPCMessageReceiver"/>
	</operation>

	<operation name="queryC">
		<messageReceiver class="org.apache.axis2.rpc.receivers.RPCMessageReceiver"/>
	</operation>

	<operation name="queryD">
		<messageReceiver class="org.apache.axis2.rpc.receivers.RPCMessageReceiver"/>
	</operation>

	<operation name="queryE">
		<messageReceiver class="org.apache.axis2.rpc.receivers.RPCMessageReceiver"/>
	</operation>
	<operation name="queryF">
		<messageReceiver class="org.apache.axis2.rpc.receivers.RPCMessageReceiver"/>
	</operation>
	<operation name="queryG">
		<messageReceiver class="org.apache.axis2.rpc.receivers.RPCMessageReceiver"/>
	</operation>
</service>
